ensauction/__init__.py
ensauction/abis.py
ensauction/auto.py
ensauction/constants.py
ensauction/registrar.py
ensauction/utils.py
ensauction-0.1.0a1.dist-info/METADATA
ensauction-0.1.0a1.dist-info/RECORD
ensauction-0.1.0a1.dist-info/WHEEL
ensauction-0.1.0a1.dist-info/top_level.txt
